Workbook

Sheet Priorización MoSCoW
A1: Plantilla de priorización de requisitos – Método MoSCoW
A3: Proyecto: | C3: GASTRO-SIM – Simulador web 3D para el entrenamiento de la toma de decisiones humano–IA en escenarios gastrointestinales
A4: Código de proyecto: | C4: GPT01-2026B-GASTRO-SIM (Equipo ITEVOLUTION)
A5: Versión / fecha: | C5: 1.3 · 11/10/2026 (v1.1: 2FA; v1.2: casos generados por IA; v1.3: categorías verificadas una a una contra la Matriz de Trazabilidad v1.3)
A6: Elaborado por: | C6: Equipo ITEVOLUTION – Director de Proyecto: Emmanuel Ospina Giraldo
A7: Aprobado por: | C7: Jair E. Sanclemente Castro – Propietario del Proyecto (Product Owner) · Fecha de aprobación: ____________
A8: Fuente: | C8: Matriz de Trazabilidad de Requisitos v1.3 y Diagrama de Casos de Uso v1.3. Esfuerzo: estimación inicial, a ajustar en el lanzamiento TSP.
A10: ID | B10: Requisito (resumen) | C10: Tipo | D10: Caso(s) de uso | E10: Entregable EDT | F10: Valor para el usuario (1–5) | G10: Riesgo de no incluirlo (1–5) | H10: Puntaje (valor × riesgo) | I10: Esfuerzo estimado (h) | J10: Categoría MoSCoW | K10: Justificación de la categoría | L10: Ciclo TSP / versión objetivo | M10: Responsable | N10: Estado
A11: RF-01.1 | B11: Permitir que una persona se registre con correo electrónico y contraseña; la cuenta nueva tendrá rol de estudiante. | C11: RF | D11: UC-01 | E11: 4.6 Plataforma e integración | F11: 3 | G11: 4 | H11: =F11*G11 -> 12 | I11: 4 | J11: Must | K11: Sin cuentas no se pueden asociar intentos ni desempeño a cada estudiante. | L11: Ciclo 1–2 (v0.5 / v0.9) | M11: Diego Agudelo | N11: Propuesto
A12: RF-01.2 | B12: Permitir iniciar y cerrar sesión, y mantener la sesión activa mientras el usuario navega. | C12: RF | D12: UC-02 | E12: 4.6 Plataforma e integración | F12: 4 | G12: 4 | H12: =F12*G12 -> 16 | I12: 3 | J12: Must | K12: El acceso controlado protege los datos registrados y separa las funciones del docente. | L12: Ciclo 1–2 (v0.5 / v0.9) | M12: Diego Agudelo | N12: Propuesto
A13: RF-01.3 | B13: Permitir que un docente/administrador asigne o retire el rol de docente a otra cuenta. | C13: RF | D13: UC-23 | E13: 4.6 Plataforma e integración | F13: 2 | G13: 2 | H13: =F13*G13 -> 4 | I13: 4 | J13: Should | K13: Al inicio los roles pueden asignarse directamente en la base de datos; la pantalla es una comodidad. | L13: Ciclo 2–3 (v0.9 / v1.0) | M13: Diego Agudelo | N13: Propuesto
A14: RF-01.4 | B14: Mostrar al primer ingreso el aviso de uso académico (no diagnóstico) y la autorización de tratamiento de datos, y registrar su aceptación. | C14: RF | D14: UC-05 | E14: 4.6 Plataforma e integración | F14: 4 | G14: 5 | H14: =F14*G14 -> 20 | I14: 3 | J14: Must | K14: Exigido por la Ley 1581 de 2012: sin consentimiento no se pueden registrar datos de los participantes. | L14: Ciclo 1–2 (v0.5 / v0.9) | M14: Diego Agudelo | N14: Propuesto
A15: RF-01.5 | B15: Exigir verificación en dos pasos (2FA) en cada inicio de sesión: después de la contraseña, el usuario ingresará un código temporal de 6 dígitos… | C15: RF | D15: UC-03 | E15: 4.6 Plataforma e integración | F15: 4 | G15: 5 | H15: =F15*G15 -> 20 | I15: 8 | J15: Must | K15: Exigido por el Product Owner: todo acceso debe tener verificación en dos pasos para proteger los datos de los participantes. | L15: Ciclo 1–2 (v0.5 / v0.9) | M15: Diego Agudelo | N15: Propuesto
A16: RF-01.6 | B16: Guiar la activación del 2FA en el primer ingreso (código QR para la aplicación autenticadora) y entregar 10 códigos de recuperación de un solo uso. | C16: RF | D16: UC-04 | E16: 4.6 Plataforma e integración | F16: 4 | G16: 5 | H16: =F16*G16 -> 20 | I16: 6 | J16: Must | K16: Sin activación guiada y códigos de recuperación, el 2FA no se puede usar ni recuperar; es parte indispensable de RF-01.5. | L16: Ciclo 1–2 (v0.5 / v0.9) | M16: Diego Agudelo | N16: Propuesto
A17: RF-01.7 | B17: Permitir que un administrador restablezca el 2FA de una cuenta que perdió su aplicación autenticadora y sus códigos, dejando registro de la acción. | C17: RF | D17: UC-23 | E17: 4.6 Plataforma e integración | F17: 3 | G17: 3 | H17: =F17*G17 -> 9 | I17: 3 | J17: Should | K17: Evita cuentas bloqueadas de forma permanente; mientras no exista, el restablecimiento puede hacerse en la consola del proveedor. | L17: Ciclo 2–3 (v0.9 / v1.0) | M17: Diego Agudelo | N17: Propuesto
A18: RF-02.1 | B18: Permitir al estudiante solicitar un caso nuevo eligiendo el nivel de dificultad (básico, intermedio o avanzado). | C18: RF | D18: UC-08 | E18: 4.2 Generador de casos con IA | F18: 4 | G18: 4 | H18: =F18*G18 -> 16 | I18: 6 | J18: Must | K18: Es la entrada al simulador: sin poder pedir un caso el estudiante no tiene nada que practicar. | L18: Ciclo 1–2 (v0.5 / v0.9) | M18: Emmanuel Ospina | N18: Propuesto
A19: RF-02.2 | B19: Permitir elegir la región anatómica del caso (esófago, estómago o duodeno); si el estudiante no la elige, el sistema la asigna al azar. | C19: RF | D19: UC-06 | E19: 4.2 Generador de casos con IA | F19: 2 | G19: 2 | H19: =F19*G19 -> 4 | I19: 4 | J19: Should | K19: Si no se elige, el sistema asigna la región; elegirla ayuda a practicar una zona concreta. | L19: Ciclo 2–3 (v0.9 / v1.0) | M19: Emmanuel Ospina | N19: Propuesto
A20: RF-02.3 | B20: Mostrar el historial de casos resueltos por el estudiante y permitir repetir un caso guardado. | C20: RF | D20: UC-07 | E20: 4.2 Generador de casos con IA | F20: 3 | G20: 2 | H20: =F20*G20 -> 6 | I20: 5 | J20: Should | K20: Repetir casos refuerza el aprendizaje, pero el flujo principal funciona sin historial. | L20: Ciclo 2–3 (v0.9 / v1.0) | M20: Emmanuel Ospina | N20: Propuesto
A21: RF-03.1 | B21: Mostrar en el navegador una escena 3D navegable del esófago, el estómago y el duodeno, sin instalar software adicional. | C21: RF | D21: UC-10 | E21: 4.1 Simulador 3D | F21: 5 | G21: 5 | H21: =F21*G21 -> 25 | I21: 30 | J21: Must | K21: El profesor exige un simulador 3D; es el núcleo del producto. | L21: Ciclo 1–2 (v0.5 / v0.9) | M21: Cristian Cruz | N21: Propuesto
A22: RF-03.2 | B22: Permitir controlar el endoscopio virtual: avanzar, retroceder y orientar la punta, con teclado y con mouse. | C22: RF | D22: UC-10 | E22: 4.1 Simulador 3D | F22: 5 | G22: 5 | H22: =F22*G22 -> 25 | I22: 16 | J22: Must | K22: Sin control del endoscopio no hay simulación. | L22: Ciclo 1–2 (v0.5 / v0.9) | M22: Cristian Cruz | N22: Propuesto
... A66: RNF-14 | B66: Un caso nuevo deberá estar listo para el estudiante en menos de 15 segundos en al menos el 90 % de las solicitudes. | C66: RNF | D66: — | E66: 4.2 Generador de casos con IA | F66: 4 | G66: 4 | H66: =F66*G66 -> 16 | I66: 4 | J66: Must | K66: Una espera larga al pedir un caso hace que el estudiante abandone la práctica. | L66: Ciclo 1–2 (v0.5 / v0.9) | M66: Emmanuel Ospina | N66: Propuesto

Sheet Resumen y control
A1: Resumen de la priorización y regla de control
A3: Categoría | B3: Requisitos RF | C3: Requisitos RNF | D3: Total requisitos | E3: % de requisitos | F3: Esfuerzo (h) | G3: % del esfuerzo
A4: Must | B4: =COUNTIFS('Priorización MoSCoW'!$J$11:$J$66,A4,'Priorización MoSCoW'!$C$11:$C$66,"RF") -> 30 | C4: =COUNTIFS('Priorización MoSCoW'!$J$11:$J$66,A4,'Priorización MoSCoW'!$C$11:$C$66,"RNF") -> 12 | D4: =B4+C4 -> 42 | E4: =IFERROR(D4/$D$8,0) -> 0.75 | F4: =SUMIF('Priorización MoSCoW'!$J$11:$J$66,A4,'Priorización MoSCoW'!$I$11:$I$66) -> 320 | G4: =IFERROR(F4/$F$8,0) -> 0.76923077
A5: Should | B5: =COUNTIFS('Priorización MoSCoW'!$J$11:$J$66,A5,'Priorización MoSCoW'!$C$11:$C$66,"RF") -> 8 | C5: =COUNTIFS('Priorización MoSCoW'!$J$11:$J$66,A5,'Priorización MoSCoW'!$C$11:$C$66,"RNF") -> 2 | D5: =B5+C5 -> 10 | E5: =IFERROR(D5/$D$8,0) -> 0.17857143 | F5: =SUMIF('Priorización MoSCoW'!$J$11:$J$66,A5,'Priorización MoSCoW'!$I$11:$I$66) -> 63 | G5: =IFERROR(F5/$F$8,0) -> 0.15144231
A6: Could | B6: =COUNTIFS('Priorización MoSCoW'!$J$11:$J$66,A6,'Priorización MoSCoW'!$C$11:$C$66,"RF") -> 4 | C6: =COUNTIFS('Priorización MoSCoW'!$J$11:$J$66,A6,'Priorización MoSCoW'!$C$11:$C$66,"RNF") -> 0 | D6: =B6+C6 -> 4 | E6: =IFERROR(D6/$D$8,0) -> 0.071428571 | F6: =SUMIF('Priorización MoSCoW'!$J$11:$J$66,A6,'Priorización MoSCoW'!$I$11:$I$66) -> 33 | G6: =IFERROR(F6/$F$8,0) -> 0.079326923
A7: Won't | B7: =COUNTIFS('Priorización MoSCoW'!$J$11:$J$66,A7,'Priorización MoSCoW'!$C$11:$C$66,"RF") -> 0 | C7: =COUNTIFS('Priorización MoSCoW'!$J$11:$J$66,A7,'Priorización MoSCoW'!$C$11:$C$66,"RNF") -> 0 | D7: =B7+C7 -> 0 | E7: =IFERROR(D7/$D$8,0) -> 0 | F7: =SUMIF('Priorización MoSCoW'!$J$11:$J$66,A7,'Priorización MoSCoW'!$I$11:$I$66) -> 0 | G7: =IFERROR(F7/$F$8,0) -> 0
A8: Total | B8: =SUM(B4:B7) -> 42 | C8: =SUM(C4:C7) -> 14 | D8: =SUM(D4:D7) -> 56 | E8: =SUM(E4:E7) -> 1 | F8: =SUM(F4:F7) -> 416 | G8: =SUM(G4:G7) -> 1
A10: Regla de control (guía DSDM / Agile Business Consortium):
A11: El esfuerzo de los requisitos Must no debería superar el 60 % del esfuerzo total, para que los Should y Could sirvan de contingencia.
A12: Límite recomendado para Must: | D12: 0.6
A13: Esfuerzo Must actual: | D13: =G4 -> 0.76923077
A14: Resultado: | D14: =IF(D13<=D12,"Cumple: hay holgura para imprevistos","Supera el límite: ver plan de acción") -> Supera el límite: ver plan de acción
A16: Capacidad del equipo (horas de desarrollo disponibles):
A17: Integrantes | D17: 5
A18: Horas por semana por integrante (Acta: 8 h) | D18: 8
A19: Semanas de construcción y pruebas (ciclos TSP) | D19: 7
A20: Capacidad total (h) | D20: =D17*D18*D19 -> 280
A21: Esfuerzo estimado de Must + Should (h) | D21: =F4+F5 -> 383
A22: Holgura de capacidad (h) | D22: =D20-D21 -> -103
A24: Plan de acción si se supera el límite o la capacidad:
A25: 1. Revisar con el Product Owner si algún Must puede pasar a Should sin afectar el propósito del simulador.
A26: 2. Usar los requisitos Should y Could como reserva: se retiran primero si el ciclo se atrasa.
A27: 3. Recalcular el esfuerzo con los datos reales de tiempo (LOGT) al cerrar el ciclo TSP 1 y repriorizar.
A28: 4. Todo cambio de categoría se registra como solicitud de cambio (Acta, sección 5.2.1) y actualiza la Matriz de Trazabilidad.

Sheet Tablero MoSCoW
A1: Tablero MoSCoW – GASTRO-SIM v1.3
A2: Vista para presentar la priorización (instantánea del 05/10/2026). Si cambia una categoría, actualice también este tablero.
A4: MUST – Debe tener | C4: SHOULD – Debería tener | E4: COULD – Podría tener | G4: WON'T – No tendrá (en esta versión)
A5: RF-01.1 | B5: Permitir que una persona se registre con correo electrónico y contraseña; la cuenta nueva tendrá rol de estudiante. | C5: RF-01.3 | D5: Permitir que un docente/administrador asigne o retire el rol de docente a otra cuenta. | E5: RF-03.7 | F5: (Opcional) simular la insuflación y la deformación de las paredes durante el recorrido. | G5: — | H5: Simulación de colonoscopia (tracto inferior)
A6: RF-01.2 | B6: Permitir iniciar y cerrar sesión, y mantener la sesión activa mientras el usuario navega. | C6: RF-01.7 | D6: Permitir que un administrador restablezca el 2FA de una cuenta que perdió su aplicación autenticadora y sus códigos, dejando registro de la acción. | E6: RF-06.3 | F6: (Opcional) mostrar un mapa de calor (Grad-CAM) como explicación visual de la recomendación. | G6: — | H6: Realidad virtual con visores
A7: RF-01.4 | B7: Mostrar al primer ingreso el aviso de uso académico (no diagnóstico) y la autorización de tratamiento de datos, y registrar su aceptación. | C7: RF-02.2 | D7: Permitir elegir la región anatómica del caso (esófago, estómago o duodeno); si el estudiante no la elige, el sistema la asigna al azar. | E7: RF-14.7 | F7: (Opcional) permitir al estudiante reportar un caso que considere incorrecto; el caso queda marcado para revisión del docente. | G7: — | H7: Uso con pacientes o datos clínicos reales
A8: RF-01.5 | B8: Exigir verificación en dos pasos (2FA) en cada inicio de sesión: después de la contraseña, el usuario ingresará un código temporal de 6 dígitos… | C8: RF-02.3 | D8: Mostrar el historial de casos resueltos por el estudiante y permitir repetir un caso guardado. | E8: RF-16 | F8: (Opcional) mostrar una tabla de clasificación entre los usuarios de un mismo grupo. | G8: — | H8: Hardware háptico y simulación física de tejidos
A9: RF-01.6 | B9: Guiar la activación del 2FA en el primer ingreso (código QR para la aplicación autenticadora) y entregar 10 códigos de recuperación de un solo uso. | C9: RF-03.6 | D9: Mostrar un minimapa con la posición actual del endoscopio dentro del tracto gastrointestinal. | G9: — | H9: Integración con la plataforma ONCO-AI
A10: RF-02.1 | B10: Permitir al estudiante solicitar un caso nuevo eligiendo el nivel de dificultad (básico, intermedio o avanzado). | C10: RF-11 | D10: Otorgar puntos, niveles e insignias según el desempeño del usuario.
A11: RF-03.1 | B11: Mostrar en el navegador una escena 3D navegable del esófago, el estómago y el duodeno, sin instalar software adicional. | C11: RF-13 | D11: Mostrar a cada estudiante un tablero con su desempeño: precisión de decisiones, detección de errores de la IA, sobre-dependencia y cobertura de…
A12: RF-03.2 | B12: Permitir controlar el endoscopio virtual: avanzar, retroceder y orientar la punta, con teclado y con mouse. | C12: RF-15 | D12: Permitir al docente exportar a CSV los registros seudonimizados de los intentos.
A13: RF-03.3 | B13: Marcar como visitados los hitos anatómicos (línea Z, cardias, fondo, cuerpo, antro, píloro y bulbo duodenal) cuando el endoscopio pase por ellos. | C13: RNF-04 | D13: Las pantallas que no son 3D deberán cargar en menos de 3 segundos.
A14: RF-03.4 | B14: Mostrar en la escena 3D el hallazgo del caso en la ubicación asignada automáticamente por el generador de casos (RF-14.3). | C14: RNF-11 | D14: El sistema publicado deberá estar disponible al menos el 95 % del tiempo durante el periodo de pruebas y la demostración final.
A15: RF-03.5 | B15: Permitir capturar un hallazgo visible en el campo de visión; al capturarlo se abre el panel de análisis del caso con la imagen endoscópica asociada.
A16: RF-04 | B16: Presentar el caso con la historia clínica sintética redactada por el agente de IA, la imagen endoscópica asociada al hallazgo y el aviso de uso…
A17: RF-05 | B17: Exigir que el usuario registre su decisión inicial y su nivel de confianza (1 a 5) antes de mostrar la recomendación de la IA.
A18: RF-06.1 | B18: Mostrar la clase sugerida por la IA y su porcentaje de confianza.
A19: RF-06.2 | B19: Marcar sobre la imagen la región de interés (ROI) en la que se basa la recomendación.
A20: RF-07.1 | B20: Permitir conversar con el tutor; cada respuesta tendrá en cuenta la historia clínica, la decisión inicial del usuario y la recomendación mostrada.
A21: RF-07.2 | B21: El tutor no debe revelar la respuesta de referencia antes de que el usuario registre su decisión final.
A22: RF-07.3 | B22: Mostrar un mensaje de respaldo y permitir continuar el caso cuando el servicio del modelo de lenguaje no responda.
A23: RF-08.1 | B23: Permitir al docente configurar el porcentaje de intentos con recomendación alterada, entre 0 % y 50 %.
A24: RF-08.2 | B24: Permitir elegir el tipo de alteración: clase incorrecta, confianza alterada o región de interés desplazada.
A25: RF-08.3 | B25: Registrar en cada intento si la recomendación fue alterada y de qué forma, sin mostrarlo al usuario antes de la retroalimentación.
A26: RF-09 | B26: Registrar la decisión final del usuario y su nivel de confianza, e identificar si cambió respecto a la decisión inicial.
... A46: RNF-14 | B46: Un caso nuevo deberá estar listo para el estudiante en menos de 15 segundos en al menos el 90 % de las solicitudes.

Sheet Criterios
A1: Criterios para asignar cada categoría MoSCoW en GASTRO-SIM
A3: Categoría | B3: Significado | C3: Pregunta de decisión para el equipo
A4: Must | B4: Imprescindible para la versión 1.0. Si falta, el producto no se puede entregar o no cumple su propósito. | C4: ¿Sin esto el simulador deja de servir para entrenar y medir la decisión humano–IA? ¿Lo exige la ley, el acta o el profesor? Si la respuesta es sí, es Must.
A5: Should | B5: Importante y con valor alto, pero existe una alternativa temporal (por ejemplo, cargar casos por archivo). | C5: ¿El flujo principal funciona sin esto, aunque sea menos cómodo? Si es así, es Should.
A6: Could | B6: Deseable. Mejora la experiencia o el realismo con bajo impacto si se omite. | C6: ¿Es un «sería bueno tener» que solo se hace si sobra tiempo? Entonces es Could.
A7: Won't | B7: Acordado explícitamente como fuera de esta versión. No se descarta para el futuro. | C7: ¿Está en el alcance excluido del acta o fuera de la capacidad del semestre? Entonces es Won't.
A10: Escalas usadas en la hoja de priorización:
A11: Valor para el usuario: 1 = casi no lo nota · 3 = útil · 5 = indispensable para su aprendizaje.
A12: Riesgo de no incluirlo: 1 = sin consecuencia · 3 = afecta la experiencia o una métrica · 5 = incumple el propósito, la ley o el acta.
A13: Puntaje = valor × riesgo (1 a 25): sirve para ordenar dentro de cada categoría, no reemplaza el criterio del equipo.
A14: Esfuerzo estimado: horas de trabajo según el juicio del equipo; se recalibra con los registros de tiempo TSP (LOGT).
A15: Procedimiento: el equipo propone la categoría → el Product Owner la aprueba → cualquier cambio posterior pasa por control de cambios.

Sheet Casos de uso
A1: Relación casos de uso – requisitos – prioridad
A3: Caso de uso | B3: Nombre | C3: Requisitos relacionados | D3: Prioridad
A4: UC-01 | B4: Registrarse | C4: RF-01.1 | D4: Must
A5: UC-02 | B5: Iniciar sesión | C5: RF-01.2 | D5: Must
A6: UC-03 | B6: Verificar segundo factor (2FA) | C6: RF-01.5 | D6: Must
A7: UC-04 | B7: Activar 2FA y códigos de recuperación | C7: RF-01.6 | D7: Must
A8: UC-05 | B8: Aceptar consentimiento informado | C8: RF-01.4 | D8: Must
A9: UC-06 | B9: Elegir región anatómica | C9: RF-02.2 | D9: Should
A10: UC-07 | B10: Consultar historial y repetir casos | C10: RF-02.3 | D10: Should
A11: UC-08 | B11: Resolver caso clínico | C11: RF-02.1, RF-03.5, RF-04, RF-12 | D11: Must
A12: UC-09 | B12: Generar caso clínico (agente de IA) | C12: RF-14.1–14.5, RF-03.4 | D12: Must
A13: UC-10 | B13: Explorar tracto gastrointestinal en 3D | C13: RF-03.1–03.4 | D13: Must
A14: UC-11 | B14: Capturar hallazgo | C14: RF-03.5 | D14: Must
... A27: UC-24 | B27: Exportar registros | C27: RF-15 | D27: Should
